yliveticker/__init__.py
yliveticker/client_code.py
yliveticker/logger.py
yliveticker/yaticker_pb2.py
yliveticker-0.3.0.dist-info/LICENSE
yliveticker-0.3.0.dist-info/METADATA
yliveticker-0.3.0.dist-info/WHEEL
yliveticker-0.3.0.dist-info/top_level.txt
yliveticker-0.3.0.dist-info/RECORD
