Metadata-Version: 2.1
Name: yliveticker
Version: 0.3.0
Summary: Live market data from Yahoo! Finance websocket
Home-page: https://github.com/yahoofinancelive/yliveticker
Author: Alexey Paramonov
Author-email: yliveticker@gmail.com
License: UNKNOWN
Platform: UNKNOWN
Classifier: Programming Language :: Python :: 3
Classifier: License :: OSI Approved :: MIT License
Classifier: Operating System :: OS Independent
Requires-Python: !=3.0.*, !=3.1.*, !=3.2.*, !=3.3.*, !=3.4.*, !=3.5.*
